django_stepped_query/__init__.py
django_stepped_query/stepped_query.py
django_stepped_query-0.0.1.dist-info/METADATA
django_stepped_query-0.0.1.dist-info/RECORD
django_stepped_query-0.0.1.dist-info/WHEEL
django_stepped_query-0.0.1.dist-info/top_level.txt
