Metadata-Version: 2.1
Name: django-stepped-query
Version: 0.0.1
Summary: Queryset Wrapper for Big Request
Home-page: https://github.com/zhangi/django_stepped_query
Author: Ivan Zhang
Author-email: sail4dream@gmail.com
License: UNKNOWN
Platform: UNKNOWN
Classifier: Programming Language :: Python :: 3
Classifier: License :: OSI Approved :: MIT License
Classifier: Operating System :: OS Independent
